_scrypt.cpython-312-x86_64-linux-gnu.so
scrypt/__init__.py
scrypt/scrypt.py
scrypt/tests/__init__.py
scrypt/tests/ciphertexts.csv
scrypt/tests/hashvectors.csv
scrypt/tests/test_params_functions.py
scrypt/tests/test_scrypt.py
scrypt/tests/test_scrypt_c_module.py
scrypt/tests/test_scrypt_py3x.py
scrypt.libs/libcrypto-bdaed0ea.so.1.1.1k
scrypt-0.9.4.dist-info/METADATA
scrypt-0.9.4.dist-info/WHEEL
scrypt-0.9.4.dist-info/top_level.txt
scrypt-0.9.4.dist-info/RECORD
scrypt-0.9.4.dist-info/licenses/LICENSE
