Metadata-Version: 2.1
Name: scrypt
Version: 0.9.4
Summary: Bindings for the scrypt key derivation function library
Home-page: https://github.com/holgern/py-scrypt
Author: Magnus Hallin
Author-email: mhallin@gmail.com
Maintainer: Holger Nahrstaedt
Maintainer-email: nahrstaedt@gmail.com
License: 2-clause BSD
Classifier: Development Status :: 4 - Beta
Classifier: Intended Audience :: Developers
Classifier: Programming Language :: Python :: 3
Classifier: Programming Language :: Python :: 3.9
Classifier: Programming Language :: Python :: 3.10
Classifier: Programming Language :: Python :: 3.11
Classifier: Programming Language :: Python :: 3.12
Classifier: Programming Language :: Python :: 3.13
Classifier: Topic :: Security :: Cryptography
Classifier: Topic :: Software Development :: Libraries
License-File: LICENSE
